buildbot_slack/__init__.py
buildbot_slack/reporter.py
buildbot_slack-0.2.3.dist-info/LICENSE
buildbot_slack-0.2.3.dist-info/METADATA
buildbot_slack-0.2.3.dist-info/WHEEL
buildbot_slack-0.2.3.dist-info/entry_points.txt
buildbot_slack-0.2.3.dist-info/top_level.txt
buildbot_slack-0.2.3.dist-info/RECORD
