Metadata-Version: 2.1
Name: buildbot-slack
Version: 0.2.3
Summary: buildbot plugin for integration with Slack.
Home-page: https://github.com/rockwelln/buildbot-slack
Author: Norman Denayer
Author-email: denayer.norman@gmail.com
License: UNKNOWN
Platform: UNKNOWN
Classifier: Development Status :: 5 - Production/Stable
Classifier: Environment :: Plugins
Classifier: Intended Audience :: Developers
Classifier: License :: OSI Approved :: MIT License
Classifier: Operating System :: Microsoft :: Windows
Classifier: Operating System :: MacOS
Classifier: Operating System :: POSIX :: Linux
Classifier: Topic :: Software Development :: Build Tools
Requires-Dist: buildbot (>=2.0.0)
Requires-Dist: treq (>=18.6)
